winzy_text_to_image/__init__.py
winzy_text_to_image-0.4.dist-info/LICENSE
winzy_text_to_image-0.4.dist-info/METADATA
winzy_text_to_image-0.4.dist-info/WHEEL
winzy_text_to_image-0.4.dist-info/entry_points.txt
winzy_text_to_image-0.4.dist-info/top_level.txt
winzy_text_to_image-0.4.dist-info/RECORD
