Metadata-Version: 2.1
Name: winzy-text-to-image
Version: 0.4
Summary: Generate text to image using pollinations.ai api
Author: Sukhbinder Singh
License: Apache-2.0
Project-URL: Homepage, https://github.com/sukhbinder/winzy-text-to-image
Project-URL: Changelog, https://github.com/sukhbinder/winzy-text-to-image/releases
Project-URL: Issues, https://github.com/sukhbinder/winzy-text-to-image/issues
Project-URL: CI, https://github.com/sukhbinder/winzy-text-to-image/actions
Classifier: License :: OSI Approved :: Apache Software License
License-File: LICENSE
Requires-Dist: winzy
Requires-Dist: requests
Provides-Extra: test
Requires-Dist: pytest ; extra == 'test'
